hacs_infrastructure/__init__.py
hacs_infrastructure/alerting.py
hacs_infrastructure/config.py
hacs_infrastructure/container.py
hacs_infrastructure/dashboards.py
hacs_infrastructure/events.py
hacs_infrastructure/health_checks.py
hacs_infrastructure/healthcare_monitoring.py
hacs_infrastructure/lifecycle.py
hacs_infrastructure/log_aggregation.py
hacs_infrastructure/monitoring.py
hacs_infrastructure/observability.py
hacs_infrastructure/protocols.py
hacs_infrastructure/service_registry.py
hacs_infrastructure-0.4.3.dist-info/METADATA
hacs_infrastructure-0.4.3.dist-info/WHEEL
hacs_infrastructure-0.4.3.dist-info/RECORD
